cbxp/__init__.py
cbxp/cbxp.py
cbxp-0.0.1.dist-info/licenses/LICENSE
cbxp-0.0.1.dist-info/METADATA
cbxp-0.0.1.dist-info/WHEEL
cbxp-0.0.1.dist-info/top_level.txt
cbxp-0.0.1.dist-info/RECORD
