Metadata-Version: 2.4
Name: cbxp
Version: 0.0.1
Summary: A unified and standardized interface for extracting z/OS control block data.
Author-email: "Leonard J. Carcaramo Jr" <lcarcaramo@ibm.com>, Elijah Swift <elijah.swift@ibm.com>, Varun Chennamadhava <varunchennamadhava@ibm.com>
Maintainer-email: "Leonard J. Carcaramo Jr" <lcarcaramo@ibm.com>, Elijah Swift <elijah.swift@ibm.com>, Varun Chennamadhava <varunchennamadhava@ibm.com>
License-Expression: Apache-2.0
Project-URL: Source, https://github.com/ambitus/cbxp
Project-URL: Issues, https://github.com/ambitus/cbxp/issues
Classifier: Development Status :: 1 - Planning
Classifier: Intended Audience :: Developers
Classifier: Operating System :: POSIX :: Other
Classifier: Programming Language :: C++
Classifier: Programming Language :: Python
Classifier: Programming Language :: Python :: 3
Classifier: Programming Language :: Python :: 3.12
Classifier: Programming Language :: Python :: 3.13
Classifier: Programming Language :: Python :: 3 :: Only
Classifier: Programming Language :: Python :: Implementation :: CPython
Classifier: Programming Language :: Python :: Implementation :: PyPy
Classifier: Topic :: System :: Hardware :: Mainframes
Requires-Python: >=3.12
License-File: LICENSE
Dynamic: license-file
